bettercaptcha/__init__.py
bettercaptcha/image.py
bettercaptcha-1.0.2.dist-info/LICENSE
bettercaptcha-1.0.2.dist-info/METADATA
bettercaptcha-1.0.2.dist-info/WHEEL
bettercaptcha-1.0.2.dist-info/top_level.txt
bettercaptcha-1.0.2.dist-info/RECORD
