Metadata-Version: 2.1
Name: bettercaptcha
Version: 1.0.2
Summary: Captcha illustrator with Pillow and Numpy for Python 3.6 or higher
Home-page: https://github.com/MagicaFreak/captchas
Author: MagicaFreak
Author-email: magicafreak@noircoding.de
License: UNKNOWN
Platform: UNKNOWN
Classifier: Programming Language :: Python :: 3
Classifier: License :: OSI Approved :: MIT License
Classifier: Operating System :: OS Independent
Requires-Python: >=3.6
License-File: LICENSE
Requires-Dist: Pillow
Provides-Extra: distortion
Requires-Dist: numpy ; extra == 'distortion'
